{
    "added": "2012-02-23T04:20:00",
    "category": "PyCon US 2010",
    "copyright_text": "Creative Commons Attribution-NonCommercial-ShareAlike 3.0",
    "description": "Sunday morning lightning talks\n\n(00:20) Tim Cooper - Lightning sound bytes\n\n(01:05) Gregg Lind, Dan Callahan - Python spring cleanup, contributing to\nFLOSS projects\n\n(05:30) Natalia Bidart, Mat\u00c3\u00adas Bordese, Facundo Batista - PyAr\n\n(10:40) D Huggins - You got your Cython in my NumPy\n\n(16:05) Ken Elkabany - PiCloud\n\n(21:20) Tim Fernando - Mobile web in Django\n\n(26:40) ? - Running a standard webapp on stackless; monkeypatching\n\n",
    "duration": null,
    "embed": "",
    "id": 261,
    "language": "English",
    "quality_notes": "",
    "recorded": "2010-02-19",
    "related_urls": [],
    "slug": "pycon-2010--sunday-morning-lightning-talks",
    "source_url": "",
    "speakers": [],
    "state": 1,
    "status": "published",
    "summary": "",
    "tags": [
        "contributing",
        "cython",
        "floss",
        "pyar",
        "pycloud",
        "pycon",
        "pycon2010",
        "stackless"
    ],
    "thumbnail_url": "http://a.images.blip.tv/Pycon-PyCon2010SundayMorningLightningTalks444-479.jpg",
    "title": "Sunday Morning Lightning Talks",
    "updated": "2014-04-08T20:28:28.204",
    "video_flv_download_only": false,
    "video_flv_length": null,
    "video_flv_url": null,
    "video_mp4_download_only": false,
    "video_mp4_length": null,
    "video_mp4_url": "http://05d2db1380b6504cc981-8cbed8cf7e3a131cd8f1c3e383d10041.r93.cf2.rackcdn.com/pycon-us-2010/261_sunday-morning-lightning-talks.m4v",
    "video_ogv_download_only": false,
    "video_ogv_length": 162933889,
    "video_ogv_url": "http://05d2db1380b6504cc981-8cbed8cf7e3a131cd8f1c3e383d10041.r93.cf2.rackcdn.com/pycon-us-2010/261_sunday-morning-lightning-talks.ogv",
    "video_webm_download_only": false,
    "video_webm_length": null,
    "video_webm_url": null,
    "whiteboard": ""
}