{"tags": [], "thumbnail_url": "http://i4.ytimg.com/vi/3Fp1zn5ao2M/hqdefault.jpg", "embed": "<object width=\"640\" height=\"390\"><param name=\"movie\" value=\"http://youtube.com/v/3Fp1zn5ao2M?version=3&amp;hl=en_US\"></param><param name=\"allowFullScreen\" value=\"true\"></param><param name=\"allowscriptaccess\" value=\"always\"></param><embed src=\"http://youtube.com/v/3Fp1zn5ao2M?version=3&amp;hl=en_US\" type=\"application/x-shockwave-flash\" width=\"640\" height=\"390\" allowscriptaccess=\"always\" allowfullscreen=\"true\"></embed></object>", "added": "2012-08-31T16:34:20", "whiteboard": "", "video_flv_length": null, "title": "Introduction to NumPy and Matplotlib", "duration": null, "description": "NumPy is the most fundamental package for scientific computing with Python. It\nadds to the Python language a data structure (the NumPy array) that has access\nto a large library of mathematical functions and operations, providing a\npowerful framework for fast computations in multiple dimensions. NumPy is the\nbasis for all SciPy packages which extends vastly the computational and\nalgorithmic capabilities of Python as well as many visualization tools like\nMatplotlib, Chaco or Mayavi.\n\nThis tutorial will teach students the fundamentals of NumPy, including fast\nvector-based calculations on numpy arrays, the origin of its efficiency and a\nshort introduction to the matplotlib plotting library. In the final section,\nmore advanced concepts will be introduced including structured arrays,\nbroadcasting and memory mapping.\n\n", "state": 1, "category": "SciPy 2012", "video_mp4_download_only": false, "video_flv_download_only": false, "video_mp4_url": "http://s3.us.archive.org/nextdayvideo/enthought/scipy_2012/Introduction_to_NumPy_and_Matplotlib.mp4?Signature=UN58jJUugfvHKtN8jEGhX98I9Ug%3D&Expires=1346380424&AWSAccessKeyId=FEWGReWX3QbNk0h3", "video_webm_length": null, "video_mp4_length": null, "recorded": "2012-07-16", "copyright_text": "CC BY-SA", "source_url": "https://www.youtube.com/watch?v=3Fp1zn5ao2M", "video_webm_url": "", "summary": "", "video_ogv_url": null, "video_ogv_length": null, "updated": "2014-04-08T20:28:27.176", "id": 1190, "related_urls": [], "slug": "introduction-to-numpy-and-matplotlib", "quality_notes": "", "video_webm_download_only": false, "video_flv_url": "", "language": "English", "video_ogv_download_only": false, "speakers": ["Eric Jones"]}