{
    "added": "2015-11-23T19:30:04.988",
    "category": "PyCon AU 2015",
    "copyright_text": "creativeCommon",
    "description": "Open edX is an open source MOOC platform. It powers courses on edx.org and those of the many adopters of the Open edX platform. Open edX is a complex platform with many interconnected parts, but the largest components are Python Django apps. \r\nThis presentation will describe the experiences of developers at The University of Queensland's UQx project from 2013 when UQ joined the edX consortium through to the present and the future. Your presenters are John Zornig, Director UQx (former Senior Architect) and Andrew Dekker Senior Developer.",
    "duration": null,
    "embed": "<iframe width=\"640\" height=\"360\" src=\"//www.youtube.com/embed/8BUuq0KVXm0\" frameborder=\"0\" allowfullscreen></iframe>",
    "id": 4039,
    "language": "English",
    "quality_notes": "",
    "recorded": "2015-08-03",
    "related_urls": [],
    "slug": "open-edx-an-edx-partner-perspective",
    "source_url": "https://www.youtube.com/watch?v=8BUuq0KVXm0",
    "speakers": [
        "John Zornig"
    ],
    "state": 1,
    "summary": "",
    "tags": [],
    "thumbnail_url": "https://i.ytimg.com/vi/8BUuq0KVXm0/hqdefault.jpg",
    "title": "Open edX: An edX partner perspective",
    "updated": "2015-11-23T19:30:04.988",
    "video_flv_download_only": false,
    "video_flv_length": null,
    "video_flv_url": null,
    "video_mp4_download_only": false,
    "video_mp4_length": null,
    "video_mp4_url": null,
    "video_ogv_download_only": false,
    "video_ogv_length": null,
    "video_ogv_url": null,
    "video_webm_download_only": false,
    "video_webm_length": null,
    "video_webm_url": null,
    "whiteboard": "needs editing"
}