{
    "added": "2013-03-13T18:55:08",
    "category": "PyCon US 2013",
    "copyright_text": "CC",
    "description": "",
    "duration": null,
    "embed": "<object width=\"640\" height=\"390\"><param name=\"movie\" value=\"http://youtube.com/v/BWyDA5y6TIg?version=3&amp;hl=en_US\"></param><param name=\"allowFullScreen\" value=\"true\"></param><param name=\"allowscriptaccess\" value=\"always\"></param><embed src=\"http://youtube.com/v/BWyDA5y6TIg?version=3&amp;hl=en_US\" type=\"application/x-shockwave-flash\" width=\"640\" height=\"390\" allowscriptaccess=\"always\" allowfullscreen=\"true\"></embed></object>",
    "id": 1729,
    "language": "English",
    "quality_notes": "",
    "recorded": "2013-03-15",
    "related_urls": [],
    "slug": "python-a-toy-language",
    "source_url": "https://www.youtube.com/watch?v=BWyDA5y6TIg",
    "speakers": [
        "David Beazley"
    ],
    "state": 1,
    "summary": "A very special guest speaker will talk about solving important \"toy\" problems with Python.\r\n",
    "tags": [
        "talk"
    ],
    "thumbnail_url": "http://i3.ytimg.com/vi/BWyDA5y6TIg/hqdefault.jpg",
    "title": "Python: A \"Toy\" Language",
    "updated": "2014-04-08T20:28:26.725",
    "video_flv_download_only": false,
    "video_flv_length": null,
    "video_flv_url": "",
    "video_mp4_download_only": true,
    "video_mp4_length": null,
    "video_mp4_url": "http://s3.us.archive.org/nextdayvideo/psf/pycon2013/Using_Python_To_Generate_Art_A.mp4?Signature=7Nc1cs0IOCoBx8ksi5b13PHc2ho%3D&Expires=1363819814&AWSAccessKeyId=FEWGReWX3QbNk0h3",
    "video_ogv_download_only": false,
    "video_ogv_length": null,
    "video_ogv_url": "",
    "video_webm_download_only": false,
    "video_webm_length": null,
    "video_webm_url": "",
    "whiteboard": ""
}