{"tags": ["talk"], "thumbnail_url": "http://i2.ytimg.com/vi/AnwkXglmLGQ/hqdefault.jpg", "embed": "<object width=\"640\" height=\"390\"><param name=\"movie\" value=\"http://youtube.com/v/AnwkXglmLGQ?version=3&amp;hl=en_US\"></param><param name=\"allowFullScreen\" value=\"true\"></param><param name=\"allowscriptaccess\" value=\"always\"></param><embed src=\"http://youtube.com/v/AnwkXglmLGQ?version=3&amp;hl=en_US\" type=\"application/x-shockwave-flash\" width=\"640\" height=\"390\" allowscriptaccess=\"always\" allowfullscreen=\"true\"></embed></object>", "added": "2013-03-13T18:55:57", "whiteboard": "", "video_flv_length": null, "title": "Fighting Cancer with Python", "duration": null, "description": "", "state": 1, "category": "PyCon US 2013", "video_mp4_download_only": true, "video_flv_download_only": false, "video_mp4_url": "http://s3.us.archive.org/nextdayvideo/psf/pycon2013/Fighting_Cancer_with_Python.mp4?Signature=QPiROY8AHtIcb7WqbsnYs0JsV5I%3D&Expires=1363664489&AWSAccessKeyId=FEWGReWX3QbNk0h3", "video_webm_length": null, "video_mp4_length": null, "recorded": "2013-03-15", "copyright_text": "CC", "source_url": "https://www.youtube.com/watch?v=AnwkXglmLGQ", "video_webm_url": null, "summary": "The \u201cWar on Cancer\u201d was declared over 40 years ago. Despite tremendous advances in understanding cancer biology and developing cancer treatments, it remains a significant cause of suffering and death. We will describe Python-based data management and analysis tools and show how they have enabled a novel flow cytometry-based technology focused on studying disease biology to improve cancer outcomes.", "video_ogv_url": null, "video_ogv_length": null, "updated": "2014-04-08T20:28:26.698", "id": 1761, "related_urls": [], "slug": "fighting-cancer-with-python", "quality_notes": "", "video_webm_download_only": false, "video_flv_url": null, "language": "English", "video_ogv_download_only": false, "speakers": ["Erik Evensen"]}