{"tags": ["pymc", "pyohio", "pyohio2011"], "thumbnail_url": "http://a.images.blip.tv/Pyohio-UsingPymcToClusterTwitterUsersANoobsPerspective618.png", "embed": "", "added": "2012-02-23T04:20:00", "whiteboard": "", "video_flv_length": null, "title": "PyOhio 2011: Using pymc to cluster twitter users -- a noob's perspective", "duration": null, "description": "Using pymc to cluster twitter users -- a noob's perspective\n\nPresented by Timmy Wilson\n\nJourney through the thoughts, hopes, and sad frustrations of an average python\ndeveloper trying to understand MCMC matrix factorization. I'll work through a\nPython implementation of the paper \"Bayesian Probabilistic Matrix\nFactorization using Markov Chain Monte Carlo\" and talk about how it applies to\nclustering a Twitter adjacency matrix.\n\n", "state": 1, "category": "PyOhio 2011", "video_mp4_download_only": false, "video_flv_download_only": false, "video_mp4_url": "http://05d2db1380b6504cc981-8cbed8cf7e3a131cd8f1c3e383d10041.r93.cf2.rackcdn.com/pyohio-2011/539_pyohio-2011-using-pymc-to-cluster-twitter-users-a-noob-s-perspective.m4v", "video_webm_length": null, "video_mp4_length": null, "recorded": null, "copyright_text": "Creative Commons Attribution 2.0", "source_url": "", "video_webm_url": null, "summary": "", "video_ogv_url": null, "video_ogv_length": 211624086, "updated": "2014-04-08T20:28:25.883", "id": 539, "related_urls": [], "slug": "pyohio-2011--using-pymc-to-cluster-twitter-users-", "quality_notes": "", "video_webm_download_only": false, "video_flv_url": null, "language": "English", "video_ogv_download_only": false, "speakers": ["Timmy Wilson"]}