{
    "added": "2015-04-22T17:59:38.628",
    "category": "PyData Paris 2015",
    "copyright_text": "youtube",
    "description": "Founded in Paris in 2009, Kpler is an intelligence company providing transparency solutions in energy markets. We develop proprietary technologies that systematically aggregate data from hundreds of sources, ranging from logistics and commercial, to governmental and shipping databases. By connecting the dots across fragmented information landscapes, we are able to deliver our clients with unique real-time market coverage.",
    "duration": null,
    "embed": "<iframe type='text/html' src='http://www.youtube.com/embed/La8VfalnHnw' width='640' height='360' frameborder='0' allowfullscreen='true'/>",
    "id": 3523,
    "language": "English",
    "quality_notes": "",
    "recorded": "2015-04-15",
    "related_urls": [],
    "slug": "python-sqlalchemy-and-scrapy-for-real-time-data",
    "source_url": "https://www.youtube.com/watch?v=La8VfalnHnw",
    "speakers": [
        "Jean Maynier"
    ],
    "state": 1,
    "status": "published",
    "summary": "",
    "tags": [],
    "thumbnail_url": "https://i.ytimg.com/vi/La8VfalnHnw/hqdefault.jpg",
    "title": "Python, SQLalchemy and Scrapy for real-time data processing at Kpler",
    "updated": "2015-04-22T17:59:38.628",
    "video_flv_download_only": false,
    "video_flv_length": null,
    "video_flv_url": null,
    "video_mp4_download_only": false,
    "video_mp4_length": null,
    "video_mp4_url": null,
    "video_ogv_download_only": false,
    "video_ogv_length": null,
    "video_ogv_url": null,
    "video_webm_download_only": false,
    "video_webm_length": null,
    "video_webm_url": null,
    "whiteboard": "needs editing"
}