{
    "added": "2012-09-06T22:33:19",
    "category": "EuroPython 2012",
    "copyright_text": "Standard YouTube License",
    "description": "The RestFS is an experimental project to develop an open-source distributed\nfilesystem for large environments. It is designed to scale up from a single\nserver to thousand of nodes and delivering a high availability storage system\nwith special features for high i/o performance and network optimization for\nwork better in WAN environment. The Restfs is pure-python, but several of the\nlibraries that it depends upon use C extensions (sometimes for speed,\nsometimes to interface to pre-existing C libraries). The Project is on the\nbeginning stage, with some technology previews released. The main\ncharacteristics of the RestFS are : - Scalability, no limits on storage and\nclients size - High availability, no single point of failure and data\nreplication - Adaptative, load balancing and uniform distribution - High\nPerformance, parallel transfer, local cache consistency , data transfer by\ndifference - Flexible, S3 compatibility interface, dedicated library for\nintegration in web server and application layer This talk describes the\narchitecture, internals of RestFS and comparison among different free software\nsolutions. The session will discuss our experience in this development and\ndetailed information on performance and scalability RestFS Introduction RestFS\nWebsite\n\n",
    "duration": null,
    "embed": "<object width=\"640\" height=\"390\"><param name=\"movie\" value=\"http://youtube.com/v/9DIpgNzC5KM?version=3&amp;hl=en_US\"></param><param name=\"allowFullScreen\" value=\"true\"></param><param name=\"allowscriptaccess\" value=\"always\"></param><embed src=\"http://youtube.com/v/9DIpgNzC5KM?version=3&amp;hl=en_US\" type=\"application/x-shockwave-flash\" width=\"640\" height=\"390\" allowscriptaccess=\"always\" allowfullscreen=\"true\"></embed></object>",
    "id": 1306,
    "language": null,
    "quality_notes": "",
    "recorded": "2012-07-05",
    "related_urls": [],
    "slug": "restfs-the-next-generation-cloud-storage",
    "source_url": "http://www.youtube.com/watch?v=9DIpgNzC5KM",
    "speakers": [
        "F Manfredi",
        "F Mosca"
    ],
    "state": 1,
    "status": "published",
    "summary": "[EuroPython 2012] F Manfredi F Mosca - 4 JULY 2012 in \"Track Ravioli\"\n\n",
    "tags": [],
    "thumbnail_url": "http://i.ytimg.com/vi/9DIpgNzC5KM/hqdefault.jpg",
    "title": "Restfs the next generation cloud storage",
    "updated": "2014-04-08T20:28:27.262",
    "video_flv_download_only": false,
    "video_flv_length": null,
    "video_flv_url": null,
    "video_mp4_download_only": false,
    "video_mp4_length": null,
    "video_mp4_url": null,
    "video_ogv_download_only": false,
    "video_ogv_length": null,
    "video_ogv_url": null,
    "video_webm_download_only": false,
    "video_webm_length": null,
    "video_webm_url": null,
    "whiteboard": ""
}