{
    "added": "2014-07-31T00:46:27.584",
    "category": "EuroPython 2014",
    "copyright_text": "http://creativecommons.org/licenses/by/3.0/",
    "description": "Presentation describes how to implement debugger for Python and has 4 parts:\r\n\r\n* Tracing Python code\r\n\r\n    Explains how to use trace function\r\n\r\n* Debugger Architecture\r\n\r\n    Explains which parts consists of a modern full-fledged debugger.\r\n\r\n* A Bit of Details\r\n\r\n    Explains how to make code to work for all python versions and implementations, survive gevent monkey-patching etc.\r\n\r\n* Cool Features\r\n\r\n    Explains how to implement exception handling and multiprocess debugging\r\n",
    "duration": null,
    "embed": "<object width=\"640\" height=\"390\"><param name=\"movie\" value=\"http://youtube.com/v/HfzdM7rsKbU?version=3&amp;hl=en_US\"></param><param name=\"allowFullScreen\" value=\"true\"></param><param name=\"allowscriptaccess\" value=\"always\"></param><embed src=\"http://youtube.com/v/HfzdM7rsKbU?version=3&amp;hl=en_US\" type=\"application/x-shockwave-flash\" width=\"640\" height=\"390\" allowscriptaccess=\"always\" allowfullscreen=\"true\"></embed></object>",
    "id": 2972,
    "language": "English",
    "quality_notes": "",
    "recorded": "2014-07-24",
    "related_urls": [],
    "slug": "python-debugger-uncovered",
    "source_url": "http://www.youtube.com/watch?v=HfzdM7rsKbU",
    "speakers": [
        "Dmitry Trofimov"
    ],
    "state": 1,
    "summary": "This talk will explain how to implement a debugger for Python. We'll start with setting a simple trace function, then look how it is implemented in modern IDEs like PyCharm and Pydev. \r\nThen we go further in the details and uncover the tricks used to implement some cool features like exception handling and multiprocess debugging.",
    "tags": [],
    "thumbnail_url": "http://i.ytimg.com/vi/HfzdM7rsKbU/hqdefault.jpg",
    "title": "Python Debugger Uncovered",
    "updated": "2014-07-31T22:56:16.256",
    "video_flv_download_only": false,
    "video_flv_length": null,
    "video_flv_url": "",
    "video_mp4_download_only": false,
    "video_mp4_length": null,
    "video_mp4_url": "",
    "video_ogv_download_only": false,
    "video_ogv_length": null,
    "video_ogv_url": "",
    "video_webm_download_only": false,
    "video_webm_length": null,
    "video_webm_url": "",
    "whiteboard": ""
}