{"tags": [], "thumbnail_url": "http://i.ytimg.com/vi/KHSXq5jfv_4/hqdefault.jpg", "embed": "<object width=\"640\" height=\"390\"><param name=\"movie\" value=\"http://youtube.com/v/KHSXq5jfv_4?version=3&amp;hl=en_US\"></param><param name=\"allowFullScreen\" value=\"true\"></param><param name=\"allowscriptaccess\" value=\"always\"></param><embed src=\"http://youtube.com/v/KHSXq5jfv_4?version=3&amp;hl=en_US\" type=\"application/x-shockwave-flash\" width=\"640\" height=\"390\" allowscriptaccess=\"always\" allowfullscreen=\"true\"></embed></object>", "added": "2014-07-31T00:46:33.875", "whiteboard": "", "video_flv_length": null, "title": "Jigna: a seamless Python-JS bridge to create rich HTML UIs for Python apps", "duration": null, "description": "", "state": 1, "category": "EuroPython 2014", "video_mp4_download_only": false, "video_flv_download_only": false, "video_mp4_url": "", "video_webm_length": null, "video_mp4_length": null, "recorded": "2014-07-22", "copyright_text": "http://creativecommons.org/licenses/by/3.0/", "source_url": "http://www.youtube.com/watch?v=KHSXq5jfv_4", "video_webm_url": "", "summary": "Jigna aims to provide an easy way to create rich user interfaces for Python applications using web technologies like HTML, CSS and Javascript, as opposed to widget based toolkits like Qt/wx or native toolkits. It provides a seamless two-way data binding between the Python model and the HTML view by creating a Python-JS communication bridge. This ensures that the view is always live as it can automatically update itself when the model changes, and update the model when user actions take place on the UI. The Jigna view can be rendered in an in-process Qt widget or over the web in a browser.", "video_ogv_url": "", "video_ogv_length": null, "updated": "2014-08-02T11:13:22.553", "id": 3027, "related_urls": [], "slug": "jigna-a-seamless-python-js-bridge-to-create-rich", "quality_notes": "", "video_webm_download_only": false, "video_flv_url": "", "language": "English", "video_ogv_download_only": false, "speakers": ["Prashant Agrawal"]}