{"tags": [], "thumbnail_url": "http://i.ytimg.com/vi/TeWfOgjFeT0/hqdefault.jpg", "embed": "<object width=\"640\" height=\"390\"><param name=\"movie\" value=\"http://youtube.com/v/TeWfOgjFeT0?version=3&amp;hl=en_US\"></param><param name=\"allowFullScreen\" value=\"true\"></param><param name=\"allowscriptaccess\" value=\"always\"></param><embed src=\"http://youtube.com/v/TeWfOgjFeT0?version=3&amp;hl=en_US\" type=\"application/x-shockwave-flash\" width=\"640\" height=\"390\" allowscriptaccess=\"always\" allowfullscreen=\"true\"></embed></object>", "added": "2014-07-31T00:46:34.590", "whiteboard": "", "video_flv_length": null, "title": "Traversing Mazes the pythonic way and other Algorithmic...", "duration": null, "description": "", "state": 1, "category": "EuroPython 2014", "video_mp4_download_only": false, "video_flv_download_only": false, "video_mp4_url": "", "video_webm_length": null, "video_mp4_length": null, "recorded": "2014-07-22", "copyright_text": "http://creativecommons.org/licenses/by/3.0/", "source_url": "http://www.youtube.com/watch?v=TeWfOgjFeT0", "video_webm_url": "", "summary": "**Graphs** define a powerful mental (and mathematical) model of structure, \r\nrepresenting the building blocks of formulations and/or solutions \r\nfor many *hard problems*. In this talk, graphs and (*some of the*) main \r\ngraph-related algorithms will be analysed from a **very pythonic** angle:\r\nthe [Zen of Python][1] (e.g., *beautiful is better than ugly*, \r\n*simple is better than complex*, *readability counts*).\r\n\r\n[1]: http://www.python.org/dev/peps/pep-0020/ \"PEP20: The Zen of Python\"", "video_ogv_url": "", "video_ogv_length": null, "updated": "2014-08-02T11:44:42.742", "id": 3034, "related_urls": [], "slug": "traversing-mazes-the-pythonic-way-and-other-algor", "quality_notes": "", "video_webm_download_only": false, "video_flv_url": "", "language": "English", "video_ogv_download_only": false, "speakers": ["Valerio Maggio"]}