{
    "added": "2012-10-08T17:39:54",
    "category": "DjangoCon 2012",
    "copyright_text": "Creative Commons Attribution license (reuse allowed",
    "description": "From the beginning, Django has been built to be designer friendly. This talk\nis meant for those who are looking to learn more about how Django empowers\ndesigners to create websites intelligently. Here is a brief outline of what\nwill be covered:\n\n  * Overview of Django's designer roots\n    * Personal background as a designer learning Django\n    * How did Django start out with designers in mind?\n    * Design methodologies\n  * How is Django designer friendly?\n\n    * Documentation overview\n    * Code examples\n      * Template inheritance and why it's awesome\n      * Overview of the built-in template tags and filters\n      * What's new in Django 1.4?\n  * Django needs designers\n\n    * How to contribute\n    * Why designers are an important part of the community\n\n",
    "duration": null,
    "embed": "<object width=\"640\" height=\"390\"><param name=\"movie\" value=\"http://youtube.com/v/nGqQC4_UV-A?version=3&amp;hl=en_US\"></param><param name=\"allowFullScreen\" value=\"true\"></param><param name=\"allowscriptaccess\" value=\"always\"></param><embed src=\"http://youtube.com/v/nGqQC4_UV-A?version=3&amp;hl=en_US\" type=\"application/x-shockwave-flash\" width=\"640\" height=\"390\" allowscriptaccess=\"always\" allowfullscreen=\"true\"></embed></object>",
    "id": 1414,
    "language": "English",
    "quality_notes": "",
    "recorded": "2012-09-06",
    "related_urls": [],
    "slug": "is-django-for-designers",
    "source_url": "http://www.youtube.com/watch?v=nGqQC4_UV-A",
    "speakers": [
        "Julia Elman"
    ],
    "state": 1,
    "summary": "How designer friendly is Django? This talk reviews the history of Django and\nhow it came to be one of the most designer friendly frameworks around. We will\nreview the Django design methodology and how simple it is for designers to get\nstarted creating and publishing their own projects.\n\n",
    "tags": [
        "django"
    ],
    "thumbnail_url": "http://i.ytimg.com/vi/nGqQC4_UV-A/hqdefault.jpg",
    "title": "Is Django for Designers?",
    "updated": "2014-04-08T20:28:26.977",
    "video_flv_download_only": false,
    "video_flv_length": null,
    "video_flv_url": null,
    "video_mp4_download_only": false,
    "video_mp4_length": null,
    "video_mp4_url": null,
    "video_ogv_download_only": false,
    "video_ogv_length": null,
    "video_ogv_url": null,
    "video_webm_download_only": false,
    "video_webm_length": null,
    "video_webm_url": null,
    "whiteboard": "needs editing"
}