{
    "added": "2015-06-14T17:04:25.729",
    "category": "PyCon Italia 2015",
    "copyright_text": "",
    "description": "Hackathons have boomed, people attending such events have been consuming thousands of APIs to power their creative projects. However, not everyone can consume APIs like a boss. Companies spend hundreds of thousands of dollars in promoting and ensuring best practices are followed when building APIs.\nIn this talk I will give you an overview of how to build a potentially successful API overnight, like hackathoneers love them and that they will consume with ease.\nA recipe for success as a takeaway from this talk will be successfully shared with the audience.\n",
    "duration": 1587,
    "embed": "",
    "id": 3612,
    "language": "Italian",
    "quality_notes": "",
    "recorded": "2015-05-29",
    "related_urls": [],
    "slug": "building-successful-apis-overnight",
    "source_url": "https://www.youtube.com/watch?v=Asfz4VVKMbY",
    "speakers": [
        "Orlando Kalossakas"
    ],
    "state": 1,
    "summary": "",
    "tags": [],
    "thumbnail_url": "https://i.ytimg.com/vi/Asfz4VVKMbY/maxresdefault.jpg",
    "title": "Building Successful APIs Overnight",
    "updated": "2015-06-14T17:04:25.729",
    "video_flv_download_only": false,
    "video_flv_length": null,
    "video_flv_url": null,
    "video_mp4_download_only": false,
    "video_mp4_length": null,
    "video_mp4_url": null,
    "video_ogv_download_only": false,
    "video_ogv_length": null,
    "video_ogv_url": null,
    "video_webm_download_only": false,
    "video_webm_length": null,
    "video_webm_url": null,
    "whiteboard": ""
}