{
    "added": "2014-11-26T17:50:51.179",
    "category": "PyCon Ukraine 2014",
    "copyright_text": "youtube",
    "description": "This report analyzes practical example of Clope clusterization algorythm, as a way of building model database using similar items given unknown cluster quantity. I will try to shed some light on Python's advantages and drawbacks in this task's implementation as well as some ways of scaling, optimizing and distributing the calculations, using alternative implementations of Python(PyPy, Stackless, etc.).",
    "duration": null,
    "embed": "<iframe type='text/html' src='http://www.youtube.com/embed/o_wEh-spa9I' width='640' height='360' frameborder='0' allowfullscreen='true'/>",
    "id": 3356,
    "language": "Russian",
    "quality_notes": "",
    "recorded": "2014-11-18",
    "related_urls": [],
    "slug": "data-mining-python",
    "source_url": "https://www.youtube.com/watch?v=o_wEh-spa9I",
    "speakers": [
        "Vitaly Haritonskiy"
    ],
    "state": 1,
    "summary": "",
    "tags": [],
    "thumbnail_url": "https://i.ytimg.com/vi/o_wEh-spa9I/hqdefault.jpg",
    "title": "Data Mining \u043d\u0430 Python",
    "updated": "2014-11-27T16:16:12.784",
    "video_flv_download_only": false,
    "video_flv_length": null,
    "video_flv_url": "",
    "video_mp4_download_only": false,
    "video_mp4_length": null,
    "video_mp4_url": "",
    "video_ogv_download_only": false,
    "video_ogv_length": null,
    "video_ogv_url": "",
    "video_webm_download_only": false,
    "video_webm_length": null,
    "video_webm_url": "",
    "whiteboard": ""
}