{"tags": ["pyconza", "pyconza2012"], "thumbnail_url": "http://archive.org/download/pyconza2012-howto-bar/pyconza2012-howto-bar.thumbs/pyconza2012-howto-bar_000206.jpg", "embed": "", "added": "2015-09-19T18:55:59.917", "whiteboard": "ia scrape", "video_flv_length": null, "title": "PyConZA 2012: How to open a bar in Python", "duration": null, "description": "", "state": 1, "category": "PyCon ZA 2012", "video_mp4_download_only": false, "video_flv_download_only": false, "video_mp4_url": "", "video_webm_length": null, "video_mp4_length": null, "recorded": "2012-10-04", "copyright_text": "http://creativecommons.org/licenses/by/3.0/", "source_url": "http://archive.org/details/pyconza2012-howto-bar", "video_webm_url": "", "summary": "How to open a bar in Python: Edward van Kuik's talk at PyConZA 2012", "video_ogv_url": "http://archive.org/download/pyconza2012-howto-bar/pyconza2012-howto-bar.ogv", "video_ogv_length": null, "updated": "2015-09-19T19:11:14.609", "id": 3885, "related_urls": [], "slug": "pyconza-2012-how-to-open-a-bar-in-python", "quality_notes": "", "video_webm_download_only": false, "video_flv_url": "", "language": "English", "video_ogv_download_only": false, "speakers": ["Edward van Kuik"]}