{"tags": [], "thumbnail_url": "https://i.ytimg.com/vi/Mhk-71Xy9Qk/hqdefault.jpg", "embed": "", "added": "2015-08-10T15:48:32.646", "whiteboard": "", "video_flv_length": null, "title": "An Iterative Approach to Inverse Problems using Python's Numpy", "duration": 1774, "description": "This is a talk about inverse problems and improving on past algorithms that have focused on inverse problems in math, data science, tomography, and image processing. We use a new iterative method coded in Python's Numpy and show it's ability to recover images compared to previous approaches. \r\n\r\n", "state": 1, "category": "PyGotham 2015", "video_mp4_download_only": false, "video_flv_download_only": false, "video_mp4_url": "http://64966d3674e0a64d8f4a-47c94b14ef8e1f83d5390cdb0629c6ed.r53.cf2.rackcdn.com/pygotham-2015/3800_An_Iterative_Approach_to_Inverse_Problems_using_Py.mp4", "video_webm_length": null, "video_mp4_length": null, "recorded": "2015-08-16", "copyright_text": "CC BY-SA", "source_url": "http://youtu.be/Mhk-71Xy9Qk", "video_webm_url": null, "summary": "", "video_ogv_url": null, "video_ogv_length": null, "updated": "2015-09-14T13:15:24.333", "id": 3800, "related_urls": [], "slug": "an-iterative-approach-to-inverse-problems-using-p", "quality_notes": "", "video_webm_download_only": false, "video_flv_url": null, "language": "English", "video_ogv_download_only": false, "speakers": ["Katya Vasilaky"]}